{"series": [{"data": [{"x": "autorickshaw", "y": 5.0}, {"x": "bus", "y": 10.5}, {"x": "car", "y": 4.43}, {"x": "mini-bus", "y": 6.6}, {"x": "motorcycle", "y": 1.94}, {"x": "scooter", "y": 1.68}, {"x": "truck", "y": 9.08}]}], "options": {"chart": {"type": "treemap", "height": 430}, "legend": {"show": false}, "plotOptions": {"treemap": {"distributed": true, "enableShades": false}}, "title": {"text": "Average area of class objects on image", "align": "left"}, "colors": ["#ffe119", "#0082c8", "#3cb44b", "#e6194b", "#911eb4", "#f58230", "#46f0f0"], "tooltip": {"y": {}}}, "type": "treemap", "height": 350, "sly_options": {"tooltip": "Average area of class objects on image is {y}%"}}